ndx_bipolar_scheme/__init__.py
ndx_bipolar_scheme/bipolar_scheme.py
ndx_bipolar_scheme/spec/ndx-bipolar-scheme.extensions.yaml
ndx_bipolar_scheme/spec/ndx-bipolar-scheme.namespace.yaml
tests/__init__.py
tests/test_ext.py
ndx_bipolar_scheme-0.3.1.dist-info/LICENSE
ndx_bipolar_scheme-0.3.1.dist-info/METADATA
ndx_bipolar_scheme-0.3.1.dist-info/WHEEL
ndx_bipolar_scheme-0.3.1.dist-info/top_level.txt
ndx_bipolar_scheme-0.3.1.dist-info/RECORD
