Metadata-Version: 2.1
Name: ndx-bipolar-scheme
Version: 0.3.1
Summary: An NWB extension for storing bipolar scheme
Home-page: https://github.com/catalystneuro/ndx-bipolar-scheme
Author: Ben Dichter, Armin Najarpour, Ryan Ly
Author-email: ben.dichter@catalystneuro.com
License: BSD 3-Clause
Platform: UNKNOWN
Classifier: Intended Audience :: Developers
Classifier: Intended Audience :: Science/Research
Requires-Dist: pynwb (>=1.1.2)
